setup.py
ryLib/__init__.py
ryLib/ai.py
ryLib/info.py
ryLib/math.py
ryLib/re.py
ryLib/std.py
ryLib/wry.py
ryLib.egg-info/PKG-INFO
ryLib.egg-info/SOURCES.txt
ryLib.egg-info/dependency_links.txt
ryLib.egg-info/top_level.txt