Metadata-Version: 1.1
Name: ryLib
Version: 1.0.1
Summary: 若宇工作室官方库
Home-page: https://github.com/
Author: 若宇 王
Author-email: wangkang@139.com
License: UNKNOWN
Platform: UNKNOWN
Classifier: Programming Language :: Python :: 3
Classifier: License :: OSI Approved :: MIT License
Classifier: Operating System :: OS Independent
